<?xml version='1.0' encoding='UTF-8'?>
<LanguageData>
  <!--EN: caves-->
  <!--VI: Hang động-->
  <Caves.label>TODO</Caves.label>
  <!--EN: Small cave networks can be found within the rocks.-->
  <!--VI: Mạng lưới hang động nhỏ có thể được tìm thấy trong các tảng đá.-->
  <Caves.description>TODO</Caves.description>
  <!--EN: coast-->
  <!--VI: bờ biển-->
  <Coast.label>TODO</Coast.label>
  <!--EN: This tile borders the coast.-->
  <!--VI: Gạch này giáp bờ biển.-->
  <Coast.description>TODO</Coast.description>
  <!--EN: mountain-->
  <!--VI: núi-->
  <Mountain.label>TODO</Mountain.label>
  <!--EN: A mountain fills one side of this tile.-->
  <!--VI: Một ngọn núi lấp đầy một bên của viên gạch này.-->
  <Mountain.description>TODO</Mountain.description>
  <!--EN: river-->
  <!--VI: sông-->
  <River.label>TODO</River.label>
  <!--EN: A stream of fresh water flows through here.-->
  <!--VI: Một dòng nước ngọt chảy qua đây.-->
  <River.description>TODO</River.description>
  <!--EN: underground cave-->
  <!--VI: Hang động ngầm-->
  <UndergroundCave.label>TODO</UndergroundCave.label>
</LanguageData>
