<?xml version="1.0" encoding="utf-8" ?>
<LanguageData>

  <!-- temperate forest -->
  <TemperateForest.label>rừng ôn đới</TemperateForest.label>
  <!-- Forests of deciduous trees interspersed with fertile clearings. Many species of animals move around among the trees and on the plains. -->
  <TemperateForest.description>Nơi rừng cây ôn đới xen lẫn với những vùng đất đai màu mỡ. Động thực vật nơi đây đa dạng và phong phú.</TemperateForest.description>

  <!-- temperate swamp -->
  <TemperateSwamp.label>đầm lầy ôn đới</TemperateSwamp.label>
  <!-- Wetlands choked with vegetation and disease. Dense overgrowth makes it hard to move around, and clearing areas for building takes a long time. Much of the terrain is too marshy to support heavy structures. -->
  <TemperateSwamp.description>Vùng đất đầm lầy đầy cây cỏ là nơi thích hợp để muỗi trú ngụ - nguyên nhân chính dẫn đến việc người dân dễ mắc dịch bệnh hơn. Ngoài ra, việc "xưng vương" ở khu này khá phức tạp và tốn thời gian do cả vùng đa phần bao phủ bởi cây cỏ và đầm lầy rộng lớn.</TemperateSwamp.description>

</LanguageData>
